{
  "id": 795,
  "name": "Antoine Poinsot",
  "username": "AntoineP",
  "avatar_template": "/user_avatar/delvingbitcoin.org/antoinep/{size}/483_2.png",
  "created_at": "2023-12-19T14:55:00.013Z",
  "cooked": "<p>What Pieter said. Plus not revealing it to the whole world by default doesn\u2019t make it unprovable.</p>",
  "post_number": 6,
  "post_type": 1,
  "posts_count": 30,
  "updated_at": "2023-12-19T14:55:19.912Z",
  "reply_count": 0,
  "reply_to_post_number": 4,
  "quote_count": 0,
  "incoming_link_count": 1,
  "reads": 66,
  "readers_count": 65,
  "score": 33.2,
  "yours": false,
  "topic_id": 304,
  "topic_slug": "unspendable-keys-in-descriptors",
  "topic_title": "Unspendable keys in descriptors",
  "topic_html_title": "Unspendable keys in descriptors",
  "category_id": 8,
  "display_username": "Antoine Poinsot",
  "primary_group_name": null,
  "flair_name": "wg-consensus-cleanup",
  "flair_url": "/uploads/default/original/1X/856d779f9ec58484f3a96285a21a813538b689f6.png",
  "flair_bg_color": "",
  "flair_color": "",
  "flair_group_id": 43,
  "badges_granted": [],
  "version": 1,
  "can_edit": false,
  "can_delete": false,
  "can_recover": false,
  "can_see_hidden_post": false,
  "can_wiki": false,
  "user_title": "Regular",
  "title_is_group": false,
  "reply_to_user": {
    "id": 92,
    "username": "josibake",
    "name": "josie",
    "avatar_template": "/user_avatar/delvingbitcoin.org/josibake/{size}/83_2.png"
  },
  "bookmarked": false,
  "raw": "What Pieter said. Plus not revealing it to the whole world by default doesn't make it unprovable.",
  "actions_summary": [
    {
      "id": 2,
      "count": 1
    }
  ],
  "moderator": false,
  "admin": false,
  "staff": false,
  "user_id": 12,
  "hidden": false,
  "trust_level": 3,
  "deleted_at": null,
  "user_deleted": false,
  "edit_reason": null,
  "can_view_edit_history": true,
  "wiki": false,
  "excerpt": "What Pieter said. Plus not revealing it to the whole world by default doesn\u2019t make it unprovable.",
  "truncated": true,
  "post_url": "/t/unspendable-keys-in-descriptors/304/6",
  "reactions": [
    {
      "id": "+1",
      "type": "emoji",
      "count": 1
    }
  ],
  "current_user_reaction": null,
  "reaction_users_count": 1,
  "current_user_used_main_reaction": false,
  "can_accept_answer": false,
  "can_unaccept_answer": false,
  "accepted_answer": false,
  "topic_accepted_answer": null
}