{
  "id": 3082,
  "name": "Murch",
  "username": "murch",
  "avatar_template": "/user_avatar/delvingbitcoin.org/murch/{size}/139_2.png",
  "created_at": "2024-08-29T16:44:21.544Z",
  "cooked": "<p>I would guess that the five minute snapshot interval could introduce a lot of noise especially for full-rbf replacements. My suspicion would be that transactions that have been full-rbf replaced are much more likely to be replaced another time within the next few minutes than transactions that were not get replaced. In that case they would show up as missing in both configurations.\nI guess what you really would want is to measure how many transactions had to be retrieved from peers after a block announcement.</p>\n<p><a class=\"mention\" href=\"/u/0xb10c\">@0xB10C</a>, was it you that published some numbers in that regard recently?</p>",
  "post_number": 6,
  "post_type": 1,
  "updated_at": "2024-08-29T16:44:21.544Z",
  "reply_count": 0,
  "reply_to_post_number": 5,
  "quote_count": 0,
  "incoming_link_count": 1,
  "reads": 10,
  "readers_count": 9,
  "score": 7.0,
  "yours": false,
  "topic_id": 1077,
  "topic_slug": "casual-research-on-running-mempoolfullrbf",
  "topic_title": "Casual research on running `mempoolfullrbf`",
  "topic_html_title": "Casual research on running `mempoolfullrbf`",
  "category_id": 8,
  "display_username": "Murch",
  "primary_group_name": null,
  "flair_name": null,
  "flair_url": null,
  "flair_bg_color": null,
  "flair_color": null,
  "flair_group_id": null,
  "version": 1,
  "can_edit": false,
  "can_delete": false,
  "can_recover": false,
  "can_see_hidden_post": false,
  "can_wiki": false,
  "user_title": "",
  "reply_to_user": {
    "username": "valuedmammal",
    "name": "",
    "avatar_template": "/letter_avatar_proxy/v4/letter/v/c6cbf5/{size}.png"
  },
  "bookmarked": false,
  "raw": "I would guess that the five minute snapshot interval could introduce a lot of noise especially for full-rbf replacements. My suspicion would be that transactions that have been full-rbf replaced are much more likely to be replaced another time within the next few minutes than transactions that were not get replaced. In that case they would show up as missing in both configurations.\nI guess what you really would want is to measure how many transactions had to be retrieved from peers after a block announcement.\n\n@0xB10C, was it you that published some numbers in that regard recently?",
  "actions_summary": [],
  "moderator": false,
  "admin": false,
  "staff": false,
  "user_id": 58,
  "hidden": false,
  "trust_level": 3,
  "deleted_at": null,
  "user_deleted": false,
  "edit_reason": null,
  "can_view_edit_history": true,
  "wiki": false,
  "reactions": [],
  "current_user_reaction": null,
  "reaction_users_count": 0,
  "current_user_used_main_reaction": false
}