{
  "id": 3907,
  "name": "David A. Harding",
  "username": "harding",
  "avatar_template": "/user_avatar/delvingbitcoin.org/harding/{size}/925_2.png",
  "created_at": "2024-12-31T20:04:34.026Z",
  "cooked": "<aside class=\"quote no-group\" data-username=\"moonsettler\" data-post=\"1\" data-topic=\"1344\">\n<div class=\"title\">\n<div class=\"quote-controls\"></div>\n<img loading=\"lazy\" alt=\"\" width=\"24\" height=\"24\" src=\"https://delvingbitcoin.org/user_avatar/delvingbitcoin.org/moonsettler/48/38_2.png\" class=\"avatar\"> moonsettler:</div>\n<blockquote>\n<ul>\n<li><code>n = 0</code> return the SUM of all input amounts with same script</li>\n<li><code>n &lt; 0</code> return the SUM of last abs(n) input amounts including current input</li>\n<li><code>n &gt; 0</code> return the SUM of first n input amounts of the transaction</li>\n</ul>\n</blockquote>\n</aside>\n<p>Does <code>OP_INPUTAMOUNTS</code> return values over 31 bits (~21 BTC)?  Does <code>OP_TEMPLATEHASH</code> accept input amounts over 31 bits?</p>",
  "post_number": 4,
  "post_type": 1,
  "updated_at": "2024-12-31T20:04:34.026Z",
  "reply_count": 1,
  "reply_to_post_number": null,
  "quote_count": 1,
  "incoming_link_count": 0,
  "reads": 11,
  "readers_count": 10,
  "score": 21.6,
  "yours": false,
  "topic_id": 1344,
  "topic_slug": "ctv-op-templatehash-and-op-inputamounts",
  "topic_title": "CTV++ OP_TEMPLATEHASH and OP_INPUTAMOUNTS",
  "topic_html_title": "CTV++ OP_TEMPLATEHASH and OP_INPUTAMOUNTS",
  "category_id": 7,
  "display_username": "David A. Harding",
  "primary_group_name": null,
  "flair_name": null,
  "flair_url": null,
  "flair_bg_color": null,
  "flair_color": null,
  "flair_group_id": null,
  "badges_granted": [],
  "version": 1,
  "can_edit": false,
  "can_delete": false,
  "can_recover": false,
  "can_see_hidden_post": false,
  "can_wiki": false,
  "user_title": null,
  "bookmarked": false,
  "raw": "[quote=\"moonsettler, post:1, topic:1344\"]\n* `n = 0` return the SUM of all input amounts with same script\n* `n < 0` return the SUM of last abs(n) input amounts including current input\n* `n > 0` return the SUM of first n input amounts of the transaction\n[/quote]\n\nDoes `OP_INPUTAMOUNTS` return values over 31 bits (~21 BTC)?  Does `OP_TEMPLATEHASH` accept input amounts over 31 bits?",
  "actions_summary": [
    {
      "id": 2,
      "count": 1
    }
  ],
  "moderator": false,
  "admin": false,
  "staff": false,
  "user_id": 6,
  "hidden": false,
  "trust_level": 3,
  "deleted_at": null,
  "user_deleted": false,
  "edit_reason": null,
  "can_view_edit_history": true,
  "wiki": false,
  "reactions": [
    {
      "id": "heart",
      "type": "emoji",
      "count": 1
    }
  ],
  "current_user_reaction": null,
  "reaction_users_count": 1,
  "current_user_used_main_reaction": false
}