{
  "id": 1533,
  "name": "Bastien Teinturier",
  "username": "t-bast",
  "avatar_template": "/user_avatar/delvingbitcoin.org/t-bast/{size}/98_2.png",
  "created_at": "2024-02-13T16:34:15.113Z",
  "cooked": "<aside class=\"quote no-group\" data-username=\"sdaftuar\" data-post=\"40\" data-topic=\"340\">\n<div class=\"title\">\n<div class=\"quote-controls\"></div>\n<img loading=\"lazy\" alt=\"\" width=\"24\" height=\"24\" src=\"https://delvingbitcoin.org/letter_avatar_proxy/v4/letter/s/0ea827/48.png\" class=\"avatar\"> sdaftuar:</div>\n<blockquote>\n<p>then it would seem that the downside from having to first consolidate your UTXOs down to 1 in a separate transaction, get that confirmed, and then use that to CPFP is not so large, in percentage terms?</p>\n</blockquote>\n</aside>\n<p>I agree, this is somewhat simple logic that can be easily implemented to handle those rare cases. We must make sure we don\u2019t forget to implement this though!</p>",
  "post_number": 41,
  "post_type": 1,
  "updated_at": "2024-02-13T16:34:15.113Z",
  "reply_count": 0,
  "reply_to_post_number": 40,
  "quote_count": 1,
  "incoming_link_count": 0,
  "reads": 8,
  "readers_count": 7,
  "score": 16.6,
  "yours": false,
  "topic_id": 340,
  "topic_slug": "v3-transaction-policy-for-anti-pinning",
  "topic_title": "V3 transaction policy for anti-pinning",
  "topic_html_title": "V3 transaction policy for anti-pinning",
  "category_id": 7,
  "display_username": "Bastien Teinturier",
  "primary_group_name": null,
  "flair_name": null,
  "flair_url": null,
  "flair_bg_color": null,
  "flair_color": null,
  "flair_group_id": null,
  "version": 1,
  "can_edit": false,
  "can_delete": false,
  "can_recover": false,
  "can_see_hidden_post": false,
  "can_wiki": false,
  "user_title": null,
  "bookmarked": false,
  "raw": "[quote=\"sdaftuar, post:40, topic:340\"]\nthen it would seem that the downside from having to first consolidate your UTXOs down to 1 in a separate transaction, get that confirmed, and then use that to CPFP is not so large, in percentage terms?\n[/quote]\n\nI agree, this is somewhat simple logic that can be easily implemented to handle those rare cases. We must make sure we don't forget to implement this though!",
  "actions_summary": [
    {
      "id": 2,
      "count": 1
    }
  ],
  "moderator": false,
  "admin": false,
  "staff": false,
  "user_id": 101,
  "hidden": false,
  "trust_level": 3,
  "deleted_at": null,
  "user_deleted": false,
  "edit_reason": null,
  "can_view_edit_history": true,
  "wiki": false,
  "reactions": [
    {
      "id": "+1",
      "type": "emoji",
      "count": 1
    }
  ],
  "current_user_reaction": null,
  "reaction_users_count": 1,
  "current_user_used_main_reaction": false
}