{
  "id": 1587,
  "name": "salvatoshi",
  "username": "salvatoshi",
  "avatar_template": "/user_avatar/delvingbitcoin.org/salvatoshi/{size}/72_2.png",
  "created_at": "2024-02-16T12:45:06.350Z",
  "cooked": "<p>It\u2019s definitely going to be <em>painful</em> to implement, but still it seems <em>feasible</em>.</p>\n<p>Binary operations are going to be the annoying part, but it should be fairly straightforward to obtain them with arithmetic operations working bit-by-bit, and possibly more efficiently with smarter tricks like <a href=\"https://github.com/coins/bitcoin-scripts/blob/405f3b0dbf64115eab7035482397b322822c6d19/op_lookup.md\" rel=\"noopener nofollow ugc\">lookup tables</a>.</p>",
  "post_number": 20,
  "post_type": 1,
  "updated_at": "2024-02-16T12:50:10.556Z",
  "reply_count": 1,
  "reply_to_post_number": 19,
  "quote_count": 0,
  "incoming_link_count": 0,
  "reads": 8,
  "readers_count": 7,
  "score": 6.4,
  "yours": false,
  "topic_id": 236,
  "topic_slug": "lamport-signatures-and-other-cat-tricks",
  "topic_title": "Lamport signatures and other CAT tricks",
  "topic_html_title": "Lamport signatures and other CAT tricks",
  "category_id": 7,
  "display_username": "salvatoshi",
  "primary_group_name": null,
  "flair_name": null,
  "flair_url": null,
  "flair_bg_color": null,
  "flair_color": null,
  "flair_group_id": null,
  "version": 2,
  "can_edit": false,
  "can_delete": false,
  "can_recover": false,
  "can_see_hidden_post": false,
  "can_wiki": false,
  "user_title": null,
  "reply_to_user": {
    "username": "moonsettler",
    "name": "moonsettler",
    "avatar_template": "/user_avatar/delvingbitcoin.org/moonsettler/{size}/38_2.png"
  },
  "bookmarked": false,
  "raw": "It's definitely going to be _painful_ to implement, but still it seems _feasible_.\n\nBinary operations are going to be the annoying part, but it should be fairly straightforward to obtain them with arithmetic operations working bit-by-bit, and possibly more efficiently with smarter tricks like [lookup tables](https://github.com/coins/bitcoin-scripts/blob/405f3b0dbf64115eab7035482397b322822c6d19/op_lookup.md).",
  "actions_summary": [],
  "moderator": false,
  "admin": false,
  "staff": false,
  "user_id": 81,
  "hidden": false,
  "trust_level": 1,
  "deleted_at": null,
  "user_deleted": false,
  "edit_reason": "Github link was replaced with a permanent link",
  "can_view_edit_history": true,
  "wiki": false,
  "reactions": [
    {
      "id": "heart",
      "type": "emoji",
      "count": 1
    }
  ],
  "current_user_reaction": null,
  "reaction_users_count": 1,
  "current_user_used_main_reaction": false
}