{
  "id": 1547,
  "name": "Juan Galt",
  "username": "juangalt",
  "avatar_template": "/user_avatar/delvingbitcoin.org/juangalt/{size}/354_2.png",
  "created_at": "2024-02-13T20:15:48.223Z",
  "cooked": "<p>Seems like such a covenant simply makes a KYC\u2019d coins more efficient for such a government institution, but this evil construct is already possible anyway with standard enterprise Bitcoin software, hardware and best practices.</p>\n<p>On the other hand, can the terms of this covenant be publicly verifiable by the public? If so, such a covenant would be restrained by it\u2019s own structure and rules. In other words, changes to it\u2019s terms would be public when implemented, where as the terms and rules of a multisig KYC\u2019d coin pool are entirely arbitrary to the key holders.</p>\n<p>If those assumptions are correct, I think I prefer covenant KYC pools than multisig ones.</p>",
  "post_number": 8,
  "post_type": 1,
  "updated_at": "2024-02-13T20:15:48.223Z",
  "reply_count": 0,
  "reply_to_post_number": 7,
  "quote_count": 0,
  "incoming_link_count": 0,
  "reads": 2,
  "readers_count": 1,
  "score": 0,
  "yours": false,
  "topic_id": 556,
  "topic_slug": "perpetually-kycd-coins-using-evil-covenants",
  "topic_title": "Perpetually KYC'd Coins Using Evil Covenants",
  "topic_html_title": "Perpetually KYC&rsquo;d Coins Using Evil Covenants",
  "category_id": 7,
  "display_username": "Juan Galt",
  "primary_group_name": null,
  "flair_name": null,
  "flair_url": null,
  "flair_bg_color": null,
  "flair_color": null,
  "flair_group_id": null,
  "version": 1,
  "can_edit": false,
  "can_delete": false,
  "can_recover": false,
  "can_see_hidden_post": false,
  "can_wiki": false,
  "user_title": null,
  "reply_to_user": {
    "username": "RobinLinus",
    "name": "Robin Linus",
    "avatar_template": "/user_avatar/delvingbitcoin.org/robinlinus/{size}/130_2.png"
  },
  "bookmarked": false,
  "raw": "Seems like such a covenant simply makes a KYC'd coins more efficient for such a government institution, but this evil construct is already possible anyway with standard enterprise Bitcoin software, hardware and best practices. \n\nOn the other hand, can the terms of this covenant be publicly verifiable by the public? If so, such a covenant would be restrained by it's own structure and rules. In other words, changes to it's terms would be public when implemented, where as the terms and rules of a multisig KYC'd coin pool are entirely arbitrary to the key holders. \n\nIf those assumptions are correct, I think I prefer covenant KYC pools than multisig ones.",
  "actions_summary": [],
  "moderator": false,
  "admin": false,
  "staff": false,
  "user_id": 293,
  "hidden": false,
  "trust_level": 0,
  "deleted_at": null,
  "user_deleted": false,
  "edit_reason": null,
  "can_view_edit_history": true,
  "wiki": false,
  "reactions": [],
  "current_user_reaction": null,
  "reaction_users_count": 0,
  "current_user_used_main_reaction": false
}