{
  "id": 4180,
  "name": "Anthony Towns",
  "username": "ajtowns",
  "avatar_template": "/user_avatar/delvingbitcoin.org/ajtowns/{size}/417_2.png",
  "created_at": "2025-02-05T04:51:21.150Z",
  "cooked": "<aside class=\"quote no-group\" data-username=\"ajtowns\" data-post=\"20\" data-topic=\"1052\">\n<div class=\"title\">\n<div class=\"quote-controls\"></div>\n<img loading=\"lazy\" alt=\"\" width=\"24\" height=\"24\" src=\"https://delvingbitcoin.org/user_avatar/delvingbitcoin.org/ajtowns/48/417_2.png\" class=\"avatar\"> ajtowns:</div>\n<blockquote>\n<p>Not sure what it would look like in a decentralised model;</p>\n</blockquote>\n</aside>\n<p>One other thing is that FIBRE is designed for UDP transmission to avoid delays due to retransmits; so redoing it over TCP via the existing p2p network would be a pretty big loss\u2026</p>",
  "post_number": 22,
  "post_type": 1,
  "updated_at": "2025-02-05T04:51:21.150Z",
  "reply_count": 0,
  "reply_to_post_number": 20,
  "quote_count": 1,
  "incoming_link_count": 0,
  "reads": 12,
  "readers_count": 11,
  "score": 32.2,
  "yours": false,
  "topic_id": 1052,
  "topic_slug": "stats-on-compact-block-reconstructions",
  "topic_title": "Stats on compact block reconstructions",
  "topic_html_title": "Stats on compact block reconstructions",
  "category_id": 7,
  "display_username": "Anthony Towns",
  "primary_group_name": null,
  "flair_name": null,
  "flair_url": null,
  "flair_bg_color": null,
  "flair_color": null,
  "flair_group_id": null,
  "badges_granted": [],
  "version": 1,
  "can_edit": false,
  "can_delete": false,
  "can_recover": false,
  "can_see_hidden_post": false,
  "can_wiki": false,
  "user_title": null,
  "bookmarked": false,
  "raw": "[quote=\"ajtowns, post:20, topic:1052\"]\nNot sure what it would look like in a decentralised model;\n[/quote]\n\nOne other thing is that FIBRE is designed for UDP transmission to avoid delays due to retransmits; so redoing it over TCP via the existing p2p network would be a pretty big loss...",
  "actions_summary": [
    {
      "id": 2,
      "count": 2
    }
  ],
  "moderator": true,
  "admin": true,
  "staff": true,
  "user_id": 3,
  "hidden": false,
  "trust_level": 4,
  "deleted_at": null,
  "user_deleted": false,
  "edit_reason": null,
  "can_view_edit_history": true,
  "wiki": false,
  "reactions": [
    {
      "id": "+1",
      "type": "emoji",
      "count": 2
    }
  ],
  "current_user_reaction": null,
  "reaction_users_count": 2,
  "current_user_used_main_reaction": false
}