{
  "id": 2803,
  "name": "Bastien Teinturier",
  "username": "t-bast",
  "avatar_template": "/user_avatar/delvingbitcoin.org/t-bast/{size}/98_2.png",
  "created_at": "2024-06-26T11:28:27.175Z",
  "cooked": "<p>Since both the payer and recipient would need to add code to support this extension, why not simply allow paying a Bolt 12 invoice (without going through the offer / invoice_request flow)?</p>\n<p>This ensures that people who want to leverage this intermediate step only add code that is useful to later support the full Bolt 12 flow instead of changing Bolt 11?</p>",
  "post_number": 2,
  "post_type": 1,
  "updated_at": "2024-06-26T11:28:27.175Z",
  "reply_count": 0,
  "reply_to_post_number": null,
  "quote_count": 0,
  "incoming_link_count": 0,
  "reads": 8,
  "readers_count": 7,
  "score": 1.6,
  "yours": false,
  "topic_id": 991,
  "topic_slug": "blip-bolt-11-invoice-blinded-path-tagged-field",
  "topic_title": "bLIP: BOLT 11 Invoice Blinded Path Tagged Field",
  "topic_html_title": "bLIP: BOLT 11 Invoice Blinded Path Tagged Field",
  "category_id": 7,
  "display_username": "Bastien Teinturier",
  "primary_group_name": null,
  "flair_name": null,
  "flair_url": null,
  "flair_bg_color": null,
  "flair_color": null,
  "flair_group_id": null,
  "version": 1,
  "can_edit": false,
  "can_delete": false,
  "can_recover": false,
  "can_see_hidden_post": false,
  "can_wiki": false,
  "user_title": null,
  "bookmarked": false,
  "raw": "Since both the payer and recipient would need to add code to support this extension, why not simply allow paying a Bolt 12 invoice (without going through the offer / invoice_request flow)?\n\nThis ensures that people who want to leverage this intermediate step only add code that is useful to later support the full Bolt 12 flow instead of changing Bolt 11?",
  "actions_summary": [],
  "moderator": false,
  "admin": false,
  "staff": false,
  "user_id": 101,
  "hidden": false,
  "trust_level": 3,
  "deleted_at": null,
  "user_deleted": false,
  "edit_reason": null,
  "can_view_edit_history": true,
  "wiki": false,
  "reactions": [],
  "current_user_reaction": null,
  "reaction_users_count": 0,
  "current_user_used_main_reaction": false
}